{
  "track_id": "0QmlsQsdZPpRl4om1zt1x1",
  "artist": "Samantha Jade",
  "title": "Never Can Say Goodbye",
  "lyrics": "I never can say goodbye, no, no, no, I\r\nI never can say goodbye\r\nEvery time I think I've had enough\r\nAnd start heading for the door\r\nThere's a very strange vibration\n\nPiercing me right to the core\n\nIt says, \"turn around you fool\n\nYou know you love him more and more\"\n\nTell me why is it so\n\nDon't want to let you go\n\n\n\nHey, I never can say goodbye, boy\n\nOoh baby, I never can say goodbye, no, no, no, hey\n\n\n\nI never can say goodbye, oh no, I\n\nI never can say goodbye\n\n\n\nI keep thinking that our problems\n\nSoon are all gonna work out\n\nBut there's that same unhappy feeling\n\nAnd that anguish and that doubt\n\nIt's that same old dizzy hang-up\n\nI can't do with you or without\n\nTell me why is it so\n\nI don't want to let you go\n\n\n\nHey, I never can say goodbye, boy\n\nOoh baby, I never can say goodbye, no, no, no, ooh\n\nHey, I never can say goodbye, boy\n\nOoh baby, I never can say goodbye, no, no, no, no, no, no\n\n\n\nHey, I never can say goodbye, boy\n\nNo, no, no, baby, hey, I never can say goodbye, no, no, no\n\nPlease don't let me say goodbye\n\nI just cannot say goodbye",
  "source": "Lyrics OVH"
}