{
  "track_id": "0fOFX94Ky6UZ28k46HNRDl",
  "artist": "Black Veil Brides",
  "title": "Our Destiny",
  "lyrics": "Have we begun to drift away\r\nHave we learned from our mistakes\r\nWho will be the one to save our destiny\r\nAll the lights have hit our eyes\r\nAnd we said our last goodbyes\n\nWho will be the one to save our destiny\n\n\n\nOh, woah, woah, woah, oh, oh \n\nOh, woah, woah, woah, oh, oh\n\nWho will save\n\nOh, woah, woah, woah, oh, oh \n\nOh, woah, woah, woah, oh, oh\n\n\n\nThe king is dead\n\nIn our town of broken dreams\n\nThe rivers red\n\nAre we breaking at the seams\n\n\n\nBleeding out\n\nFire spreads like kerosene\n\nWe're going down\n\nWe're going down in tragedy\n\n\n\nSinging\n\nOh, woah, woah, woah, oh, oh \n\nOh, woah, woah, woah, oh, oh\n\n\n\nHave we begun to drift away\n\nHave we learned from our mistakes\n\nWho will be the one to save our destiny\n\n\n\nAll the lights have hit our eyes\n\nAnd we said our last goodbyes\n\nWho will be the one to save our destiny\n\n\n\nSound the bells\n\nFrom the dark and hallow hills\n\nHounds from hell\n\n\n\nYeah, we're goin' in for the kill\n\nNo defense\n\nWe've got nothin' left to lose\n\nBut our revenge\n\nWe'll remind them of our truth\n\n\n\nSinging\n\nOh, woah, woah, woah, oh, oh \n\nOh, woah, woah, woah, oh, oh\n\n\n\nHave we begun to drift away\n\nHave we learned from our mistakes\n\nWho will be the one to save our destiny\n\n\n\nAll the lights have hit our eyes\n\nAnd we said our last goodbyes\n\nWho will be the one to save our destiny\n\n\n\nOh, woah, woah, woah, oh, oh \n\nOh, woah, woah, woah, oh, oh\n\nOh, woah, woah, woah, oh, oh\n\nOh, woah, woah, woah, oh, oh\n\n\n\nHave we begun to drift away\n\nHave we learned from our mistakes\n\nWho will be the one to save our destiny\n\n\n\nAll the lights have hit our eyes\n\nAnd we said our last goodbyes\n\nWho will be the one to save our destiny\n\n\n\nOh, woah, woah, woah, oh, oh\n\nOh, woah, woah, woah, oh, oh\n\nWho will save\n\nOh, woah, woah, woah, oh, oh\n\nOh, woah, woah, woah, oh, oh\n\nWho will save our destiny",
  "source": "Lyrics OVH"
}