{
  "track_id": "37z1U7PORW95mDVHiKedWx",
  "artist": "LP",
  "title": "Die For Your Love",
  "lyrics": "Turn the lights up\r\nNothin' to hide from\r\nLet's see those eyes\r\nTurn your glance up\r\nGirl just man up\r\nAnd be alright\n\n\n\nLet's be old souls\n\nAnd sweep the low lows\n\nHere unto dust\n\n'Cause I'd take every bullet\n\nAnd fire one through\n\nWell I'd die for you\n\nDie for your love\n\n\n\nIf I'm gonna give myself up\n\nI will give myself up\n\nEven if I let myself go\n\nI will let myself go\n\nGot the lust my life\n\nGot that will to survive\n\nBut I'd die for your\n\nDie for your love\n\n\n\nWhoa, oh, oh, oh\n\nWhoa, oh, oh, oh\n\nI will die for your\n\nDie for your\n\nDie for your love\n\n\n\nNew beginnings\n\nNever-ending\n\nLet's take over\n\nTo the living\n\nForever giving\n\nI can see that now\n\n\n\nLet the time run\n\nWe'll let the warm sun be enough\n\n'Cause there's no chance I won't take\n\nI'd burn at the stake\n\nI would die for your\n\nDie for your love\n\n\n\nIf I'm gonna give myself up\n\nI will give myself up\n\nEven if I let myself go\n\nI will let myself go\n\nGot the lust my life\n\nGot that will to survive\n\nBut I'd die for your\n\nDie for your love\n\n\n\nWhoa, oh, oh, oh\n\nWhoa, oh, oh, oh\n\nI will die for your\n\nDie for your\n\nDie for your love",
  "source": "Lyrics OVH"
}