{
  "track_id": "4wsYjBZFPhZRjnW7RwPBxd",
  "artist": "O Rappa",
  "title": "O Salto",
  "lyrics": "As ondas de vaidades\r\nInundaram os vilarejos\r\nE minha casa se foi\r\nComo fome e banquete\r\nEntão sentei sobre as ruínas\r\nE as dores como o ferro\n\nA brasa e a pele ardiam\n\nComo o fogo dos novos tempos\n\nArdiam\n\nComo o fogo dos novos tempos\n\n\n\nE regaram as flores no deserto\n\nE regaram as flores com chuva de insetos\n\nE regaram as flores no deserto\n\nE regaram as flores com chuva de insetos\n\n\n\nMas se você ver\n\nEm seu filho\n\nUma face sua\n\nE retinas de sorte\n\nE um punhal\n\nReinar como o brilho do sol\n\nO que farias tu?\n\nSe espatifaria\n\nOu viveria o espírito santo?\n\nSe espatifaria\n\nOu viveria o espírito santo?\n\n\n\nAos jornais\n\nEu deixo meu sangue\n\nComo capital 2x\n\nE às famílias\n\nUm punhal\n\n(à corte eu deixo um sinal)\n\n\n\nE regaram as flores no deserto\n\nE regaram as flores com chuva de insetos\n\nE regaram as flores no deserto\n\nE regaram as flores com chuva de insetos\n\n\n\nAs ondas de vaidades\n\nInundaram os vilarejos\n\nE minha casa se foi\n\nComo fome e banquete\n\nEntão sentei sobre as ruínas\n\nE as dores como o ferro e\n\nA brasa e a pele ardiam\n\nComo o fogo dos novos tempos\n\nArdiam\n\nComo o fogo dos novos tempos\n\n\n\nMas se você ver\n\nEm seu filho\n\nUma face sua\n\nE retinas de sorte\n\nE um punhal\n\nReinar como o brilho do sol\n\nO que farias tu?\n\nSe espatifaria\n\nOu viveria o espírito santo?\n\nSe espatifaria\n\nOu viveria o espírito santo?\n\n\n\nAos jornais\n\nEu deixo meu sangue\n\nComo capital 2x\n\nE às famílias\n\nUm punhal\n\n(a corte eu deixo um sinal)\n\n\n\nE regaram as flores no deserto\n\nE regaram as flores com chuva de insetos\n\nE regaram as flores no deserto\n\nE regaram as flores com chuva de insetos\n\nE regaram as flores no deserto\n\nE regaram as flores com chuva de insetos\n\nE regaram as flores no deserto\n\nE regaram as flores com chuva de insetos\n\nE regaram as flores no deserto\n\nE regaram as flores com chuva de insetos",
  "source": "Lyrics OVH"
}