{
  "track_id": "6q7ZhZkvOoTKEfdkvr1Nxm",
  "artist": "Moha La Squale",
  "title": "Pas comme eux",
  "lyrics": "Il arrive à un moment où on se dit : ce que j'ai à dire n'est pas essentiel. Je ne dis pas que je n'ai jamais dit quelque chose d'essentiel, c'est pas ça. Mais, ça n'est pas un besoin précis, net. Et il faut s'taire. Un problème de méthode\r\nOn est pas comme eux\r\nJ'reviens d'loin, y'avait rien\r\nTout commence sur Paris\r\nL'histoire d'un jeune Algérien\n\nUn jeune Algérien qui s'est souvent gamelle\n\nLe dépôt, la gamelle, le dispat, la sortie\n\nAvec élégance, il s'est toujours relevé\n\nY'a que d'vant sa mère qu'il ravale sa fierté\n\nJ'ai pas d'rivaux, t'fais caca, t'es un riverain\n\nJ'm'arrête pas, j'suis une rivière\n\nT'étonnes pas, j'suis une galère\n\nJ'dirais pas qu'j'suis futé mais ma gueule, j'suis têtu\n\nJ'ai tâté l'si-fu, style de fou, spliff au bec\n\nIls ont fini d'becqueter, ma broutille est classée\n\nGuette la classe, Bendero\n\nDis pas qu'tu vends des kilos\n\nQu'ta rabla vient d'cali\n\nTon classe C, c'est une Kelo\n\nTon bi-go, il est froissé\n\nEt tu fronces les sourcils\n\nTu fronces les sourcils mais t'oses rien, sale froussard\n\nC'est La Squale, pas d'hasard\n\nJ'fous l'bazar dans l'classement\n\nJ'débite sale d'puis l'début\n\nJ'veux des tainp', j'veux l'tin-bu\n\nJ'ai cambu pour des prunes\n\nMaintenant, j'ai mon prunier\n\nPersonne m'a parrainé\n\nJ'te parie qu'ils ont seum\n\nCar j'ai du seum pas d'semi\n\nC'est réel, c'est ma vie\n\nD'vant la juge, j'ai rien vu\n\nC'est pas moi, c'est la rue\n\nEt dans cette ur, j'suis tombé\n\nDepuis l'berceau elle m'a bercé\n\nLes murs gris, c'est blasant\n\nPartout en gardav', y'a mon blaze\n\nT'es bizarre, t'fais l'enfant\n\nPour des bêtises, tu fais l'fou\n\nArrête tes foutaises\n\nMa tête, chaud j'vais t'taper\n\nTa meuf t'a trompé car tu joues d'la trompette\n\nMa gueule, elle s'trompe pas, t'fais l'tron-pa, t'es une tapette\n\nLes p'tits d'la cité te voient comme une te-pu\n\nLa Squale à 13 ans, c'est du sale sous re-pu\n\nJ'ai pas d'répit, me pose pas la question\n\nDu shit, d'la ke-skun\n\nJ'en ai bouclé des litrons\n\nJamais plaider coupable, des coups durs surmontables\n\nEt là ton pote t'a poucave, t'étais avec une pouci\n\nLes poulets l'ont farci\n\nFranc-jeu, c'est pas une farce\n\nTon ami a trahi, par principe tu l'fais pas\n\nUn rat, c'est un rat\n\nLa Squale, c'est pas une raclure\n\nJ'ai mangé des raclées\n\nBien plus chaudes qu'une raclette\n\nJ'rentrais pas dans vos fêtes\n\nT'sais bien qu'j'fêtais mon anniv'\n\nRavale ta langue, le minot a grandi\n\nLe mini, il manie\n\nBaise la mère à Tony\n\n\n\nLe mini, il manie\n\nLe minot est barjot\n\nLa Squale, Bendero\n\n22 semaines, ça freine pas\n\n24 sons en 5 mois\n\nC'tait la merde, j'y crois pas\n\nMaman, t'inquiète pas, j'suis plus fort que papa\n\nLe mini, il manie\n\nLe minot est barjot\n\nLa Squale, Bendero\n\n22 semaines, ça freine pas\n\n24 sons en 5 mois\n\nC'tait la merde, j'y crois pas\n\nMaman, t'inquiète pas, j'suis plus fort que papa\n\n\n\nSale, on a tout niqué frérot, sale\n\nMaman, t’inquiète pas, j'suis plus fort que papa, wallah\n\nSale, ma gueule\n\nIl est parti, ce vilain, mais t'auras ta villa\n\nTêtu comme Tartuffe, j'étais tout seul, moi et mon spliff\n\nMoi et c'regard pensif\n\nQui aurait cru ? Qui aurait dit ?\n\nJ'y ai cru, c'est parti\n\nMaintenant, j'vais m'faire Tony\n\nSale\n\nBah ouais, ma gueule\n\nÀ dimanche prochain\n\nLa Squale\n\nMerci à tous",
  "source": "Lyrics OVH"
}