{
  "track_id": "1KGZgFI1uOo4XYGrgeiAvE",
  "artist": "Maes",
  "title": "Switch Up",
  "lyrics": "Ah bah ouais Bersa\r\nM.A.E.S mon ami, eh, eh\r\nM.A.E.S mon ami, eh, eh\r\nDifférent, différent, Maes est différent\r\nDifférent, Maes est différent\n\nOuais j'suis posé dans l'club, gros joint d'peuf\n\nPisté par les keufs, j'ai coffré mon 9\n\nJ'ai plus l'temps des bagarres, j'te fume à pas d'heure\n\nJ'sors du mitard, j'peux t'crosser devant ta sœur\n\nTes gavas aiment la vie, les miens aiment trop la mort\n\nJ'ai même pas l'temps d'la piner, j'dois repartir encore\n\nTon patron m'a invité, il sait c'que j'lui rapporte\n\nJ'reste une heure et je quitte, ta go n'est pas d'accord, han\n\n\n\nJ'en ai vu qui ont bavé\n\n2 minutes après ils ont détalé\n\nJ'en ai vu qui ont bavé\n\n2 minutes après ils ont détalé\n\nSwitch up rebeu, switch up rebeu\n\nSwitch up rebeu, switch up rebeu\n\nSwitch up rebeu, switch up rebeu\n\nSwitch up rebeu, switch up rebeu\n\nOuais j'suis posé dans l'binks, han\n\nOuais j'suis posé dans l'binks, han\n\nOuais j'suis posé dans l'binks, han\n\nOuais j'suis posé dans l'binks\n\n\n\nPour avoir la paix, j'sais qu'il faut faire la guerre\n\nJ'ai trop connu la perte, 18 mois, même pas une perm'\n\nJ'suis né pour la victoire, baraude en vitres teintées\n\nGros j'fais pas d'teinture, à la ceinture éduqué\n\nL'opposé s'attire, si tu touches le but\n\nEvidemment qu'ça tire, j'vois qu'des fils de pute\n\nQui sucent pour un clip, mais le jour où j'glisse\n\nPlus personne au tél', t'envoies pas un Twix, eh\n\n\n\nJ'en ai vu qui ont bavé\n\n2 minutes après ils ont détalé\n\nJ'en ai vu qui ont bavé\n\n2 minutes après ils ont détalé\n\nSwitch up rebeu, switch up rebeu\n\nSwitch up rebeu, switch up rebeu\n\nSwitch up rebeu, switch up rebeu\n\nSwitch up rebeu, switch up rebeu\n\nOuais j'suis posé dans l'binks, han\n\nOuais j'suis posé dans l'binks, han\n\nOuais j'suis posé dans l'binks, han\n\nOuais j'suis posé dans l'binks, han\n\n\n\nTes ennemis sont posés avec mes gavas dans l'club\n\nTes ennemis sont posés avec mes gavas dans l'club\n\nTes ennemis sont posés avec mes gavas dans l'club\n\nTes ennemis sont posés avec mes gavas dans l'club\n\n\n\nSwitch up rebeu, switch up rebeu\n\nSwitch up rebeu, switch up\n\nSwitch up rebeu, switch up rebeu\n\nSwitch up rebeu, switch up",
  "source": "Lyrics OVH"
}