{
  "track_id": "3BFMVHgkNef58p9f620ZFm",
  "artist": "Make Mama Proud",
  "title": "Artificial",
  "lyrics": "Cual es la razon de tu decision\r\nCuanta desilucion cayo en mis hombros\r\nTriste es la realidad de tu voluntad\r\nPero una vez mas las ganas de aparentar\r\nCambiaste tu libertad\n\nPor verte\n\nComo uno mas\n\nPrefiero desencajar\n\nNo verme artificial\n\n\n\nPuedo ver tu fragilidad\n\nPuedo ver la incomodidad (artificial)\n\nPuedo ser tu fragilidad\n\nPuedo ser la incomodidad (artificial)\n\n\n\nRostros sin direccion los sueños perdidos\n\nCual es la mision si estamos dormidos\n\nSiempre esta la opcion de ser uno mismo\n\nPero una vez mas tus ganas de aparentar\n\n\n\nCambiaste tu libertad\n\nPor verte...\n\nComo uno mas\n\nPrefiero desencajar\n\nNo verme artificial\n\n\n\nPuedo ver tu fragilidad\n\nPuedo ver la incomodidad (artificial)\n\nPuedo ser tu fragilidad\n\nPuedo ser la incomodidad (artificial)",
  "source": "Lyrics OVH"
}