{
  "track_id": "22zfAKp0G8FtEe48sB44Yf",
  "artist": "Lyanno",
  "title": "No Tiene Novio",
  "lyrics": "Ly-Ly-Ly-Ly\r\nYeah, yeah, jajaja\r\nElla no tiene novio\r\nNo está pa' nadie\r\nNo está pa' ella, y pide calle\n\nLa sensación del bloque, ella e' otra cosa\n\nPor esa pelean y se ganó un par de envidiosa'\n\nEstá bien dura con su piquete\n\nDe ella se enchulan, pero ninguno le mete\n\nCon su' amiguita' algarete\n\nA nadie le debe na'\n\n\n\nYeh\n\nElla siempre dice que no\n\nQue no le importa na'\n\nNo le hable' de relación\n\nQue quiere vacilar\n\nHasta que salga el sol\n\nLo que hizo quiere olvidar\n\nNo trates de convencerla, porque ella (Ah)\n\n\n\nSiempre dice que no (Siempre dice que no)\n\nQue no le importa na' (Que no le importa na')\n\nNo le hable' de relación\n\nQue quiere vacilar (Vacilar na' má', baby)\n\nHasta que salga el sol (Hasta que salga el sol)\n\nLo que hizo quiere olvidar (Ah)\n\nNo trates de convencerla, porque ella (Oye, no trate')\n\n\n\nWuuf, No-No-Noriel\n\nElla no tiene novio, quiere vacilar na' má' (Na' má')\n\nNo tiene a nadie que le esté diciendo na' (Yeah)\n\nDice que primero muerta que sencilla (Uoh)\n\nLa labia monga la quilla porque de ninguno se deja (Uoh)\n\nY no te voy a mentir (Ajá)\n\nComo mismo llega, así mismito se va a ir (Yeah)\n\nLa chamaquita está dura, sin ir al gym (Yeah)\n\nCuando se juntan con las amiga' son como el Cartel de Medellín (Ah, ah, ah)\n\nEs má', te vo' a dar un consejo (Apunta)\n\nNo esté' atrá' de ella pa' que no haga' el papel de pendejo (Jajaja)\n\nQue de una relación no va a estar presa (No)\n\nElla siempre ha sido cazadora, ella nunca ha sido la presa\n\n\n\nElla siempre dice que no\n\nQue no le importa na'\n\nNo le hable' de relación\n\nQue quiere vacilar\n\nHasta que salga el sol\n\nLo que hizo quiere olvidar\n\nNo trates de convencerla, porque ella\n\n\n\nNo te necesita, no es de esa' loquita'\n\nElla paga el VIP, la champaña rosita\n\nYeh, buen sexo pa' vacilar ahorita\n\nNaturola, en Colombia no le hace falta una cita\n\nPorque ella compra su' cartera' Louis Vuitton\n\nLos taco' Loboutin\n\nTener una mansión\n\nUn yate pa' San Martín\n\nSin chapearsela a un don\n\nTiene una cama king, no hace falta ningún cabrón, eh\n\n\n\nBailando una diosa\n\nNo te enamore' de ella, e' peligrosa\n\nSola modela porque es otra cosa\n\nY tus ojo' veo\n\nY lo menea, pa' que la vea\n\nBailando una diosa\n\nNo te enamore' de ella, e' peligrosa\n\nSola modela porque es otra cosa\n\nY tus ojo' veo\n\nY lo menea, pa' que la vea\n\n\n\nElla siempre dice que no (Que no)\n\nQue no le importa na'\n\nNo le hable' de relación (No hable' de relación)\n\nQue quiere vacilar\n\nHasta que salga el sol\n\nLo que hizo quiere olvidar (Olvidar)\n\nNo trates de convencerla, porque ella (Ah)\n\n\n\nDile Lyanno\n\nLy-Ly, mami\n\nLyanno, mami\n\nNo-No-Noriel\n\nEl Cambio, baby, je\n\nCon los que nunca fallan\n\nSubeloNeo\n\nFreddy y Phantom, ¡wuh!\n\nPor la orillita (Emil)\n\nNo traten de imitar que ustede' no le hacen a esto como nosotro', ¿okey? Yeh\n\nEl Cambio, mami, yeh, ah, yeh\n\nEl Cambio, mami, yeh, jejeje",
  "source": "Lyrics OVH"
}