{
  "track_id": "7dFGkZbmm6cVlI28bfMaWE",
  "artist": "Joey Bada$$",
  "title": "Righteous Minds",
  "lyrics": "(Intro)\r\nYeah\r\nMake sure my shit sound tight\r\n(Verse)\r\nI never knew the world could be this mad\n\nOnly vision I had of sex was callin' me bad\n\nI never knew the world could be this cold\n\nOnly time a nigga died he was playing a role\n\nBut now niggas get their souls stole so often\n\nThey only did is offer gimits is awake in their coffin\n\nFrom NY to Compton down the hole\n\nShe said that office offers abortions\n\nWithout precaution,\n\nPower to the people,\n\nThere's too many who wanna be Jordan\n\nToo many forces thinking they could make a fortune story\n\nToo many wanna be actors instead of achiveing their masters\n\nAt least the bachelor would know too many wanna be rappers\n\nThat's just statistics they'll be steak before he'll pay Christ\n\nLike niggers in the White House supplying white towels\n\nOr Jim Crow Laws you probably missed it\n\nHard to be persistent when you tryin' to fight for your existence\n\n\n\n(Chorus)\n\nIt ain't easy living life like this\n\nWhen you tryin' to be righteous\n\nBut know a nigga might just\n\nLeave you lifeless for prices\n\nHigh tech devices\n\nSo keep your tech down\n\nOr meet your Christ\n\nIt ain't easy living life like this\n\nWhen you tryin' to be righteous\n\nBut know a nigga might just\n\nLeave you lifeless for prices\n\nHigh tech devices\n\nSo keep your tech down\n\nOr meet your Christ\n\n\n\n(Verse)\n\nPerson, mad nervous you surrender of the sturving\n\nLook them in the eyes flicks makes you die\n\nYou know you merk 'em right there\n\nPlus his hide is like right here\n\nSo you know that if you would fight fair\n\nThen you'd have him like cry scared\n\nBut don't forget to tack your heart\n\nBy your right hand\n\nSo listen loud and clear\n\nYou don't wanna lose your life there\n\nDon't you show a slight tail\n\nOr let 'em sight fear\n\nJust let 'em dissapear in the night yeah\n\nWhat your life is ,rabbi the clack is\n\nLeft alone in the apartment\n\nSomeone's been jobless someone make dollars\n\nShaking it topless and\n\nDaddy be gone said it\n\nTook off like ashes\n\nDizzy gain knowledge\n\nI'm keeping it with the synapsis\n\nSaying shit like that make you wish you were adopted\n\nTo escape the pain you joined the gang\n\nAnd get intoxicated\n\nHad no shame, nothing wrong with some Mary Jane\n\nThe only thing is you do with the game\n\n\n\n(Chorus)\n\nIt ain't easy living life like this\n\nWhen you tryin' to be righteous\n\nBut know a nigga might just\n\nLeave you lifeless for prices\n\nHigh tech devices\n\nSo keep your tech down\n\nOr meet your Christ\n\nIt ain't easy living life like this\n\nWhen you tryin' to be righteous\n\nBut know a nigga might just\n\nLeave you lifeless for prices\n\nHigh tech devices\n\nSo keep your tech down\n\nOr meet your Christ\n\n\n\n(Verse)\n\nImagine me fed up\n\nA go getter, for more cheddar\n\nPour never, no more lettuce\n\n'Cause I know no better\n\nNo error no steals\n\nNo Kirk, No Lee,no school\n\nNo OJ, no talent, know me\n\nBut if I did say act right\n\nWhat if I pack crack white\n\nWith my sack tight\n\nJoined the gang fight\n\nThey click clack tight\n\nSledding the vibe\n\nWith the black stripe\n\nAnd get my friend's the back knife\n\n'Cause that's life\n\nNigga\n\n\n\n(Chorus)\n\nIt ain't easy living life like this\n\nWhen you tryin' to be righteous\n\nBut know a nigga might just\n\nLeave you lifeless for prices\n\nHigh tech devices\n\nSo keep your tech down\n\nOr meet your Christ\n\nIt ain't easy living life like this\n\nWhen you tryin' to be righteous\n\nBut know a nigga might just\n\nLeave you lifeless for prices\n\nHigh tech devices\n\nSo keep your tech down\n\nOr meet your Christ\n\nIt ain't easy living life like this\n\nWhen you tryin' to be righteous\n\nBut know a nigga might just\n\nLeave you lifeless for prices\n\nHigh tech devices\n\nSo keep your tech down\n\nOr meet your Christ\n\nIt ain't easy living life like this\n\nWhen you tryin' to be righteous\n\nBut know a nigga might just\n\nLeave you lifeless for prices\n\nHigh tech devices\n\nSo keep your tech down\n\nOr meet your Christ",
  "source": "Lyrics OVH"
}