{
  "track_id": "5J37BSdFXwKV6lzE6WVPRA",
  "artist": "Our Last Night",
  "title": "Soul Speak",
  "lyrics": "There's too many minds around me\r\nThis company is making me crazy\r\nThere's voices in my head, breaking my spirit\r\nCan't stop wishing they were dead, don't wanna hear it\r\nOpinions in my head, my biggest fear is that they'll\n\nMultiply and spread, don't wanna feel it\n\nLooking, looking, looking over my shoulder\n\nAs paranoid, paranoid as a criminal\n\n\n\nThere's too many minds around me\n\nThis company is making me crazy\n\nAnd I know I shouldn't care what they think\n\nThere's too many minds around me\n\nI can't let my soul speak\n\nI can't let my soul speak\n\n\n\nIllusions in my head make me believe that\n\nThe monsters under my bed can hear me breathing\n\nI'm looking, looking, looking over my shoulder\n\nAs paranoid, paranoid as a criminal\n\n\n\nThere's too many minds around me\n\nThis company is making me crazy\n\nAnd I know I shouldn't care what they think\n\nThere's too many minds around me\n\nI can't let my soul speak\n\n(Soul speak, soul speak)\n\nI gotta let my soul speak\n\n(Soul speak, soul speak)\n\nGotta let my soul speak, yeah\n\n\n\nThere's too many minds around me\n\nThis company is making me crazy\n\nAnd I know I shouldn't care what they think\n\nThere's too many minds around me\n\nI can't let my soul speak\n\n(Soul speak, soul speak\n\nSoul speak, soul speak)\n\nI can't let my soul speak\n\n(I can't let my soul speak)",
  "source": "Lyrics OVH"
}