{
  "track_id": "31RtShBICxYaZbzerWBE9u",
  "artist": "Headhunterz",
  "title": "Takin' It Back",
  "lyrics": "Now we gonna do this like we used to\r\nTaking it back to the roots, you know\r\nRepeat it in your mind\r\nYou better understand\r\nWe gonna start a fire\n\nThat wasn't supposed to end\n\nWe taking it back \n\nWe taking it back \n\nWe taking it back \n\nYeah, we taking it back\n\n\n\nWe gonna keep it real\n\nThe rest down the drain\n\nWe run melodies\n\nBut you know we ain't playing\n\nWe taking it back \n\nWe taking it back \n\nWe taking it back \n\nYeah, we taking it back\n\n\n\nYeah\n\n\n\nWe taking it back\n\nCome on\n\n\n\nRepeat it in your mind\n\nYou better understand\n\nWe gonna start a fire\n\nThat wasn't supposed to end\n\nWe taking it back \n\nWe taking it back \n\nWe taking it back \n\nYeah, we taking it back\n\n\n\nWe gonna keep it real\n\nThe rest down the drain\n\nWe run melodies\n\nBut you know we ain't playing\n\nWe taking it back \n\nWe taking it back \n\nWe taking it back \n\nCome on\n\n\n\nWe taking it back \n\nWe taking it back \n\nWe taking it back \n\nHa, yeah\n\nWe taking it back \n\nWe taking it back \n\nWe taking it back \n\nLet's go\n\nWe taking it back \n\nWe taking it back \n\nWe taking it back \n\nHa, yeah\n\nWe ain't playing no games no more",
  "source": "Lyrics OVH"
}