{
  "track_id": "0Kb0hsNss3OBz0fTd6rvmw",
  "artist": "MYMP",
  "title": "Sa'Yo Lamang",
  "lyrics": "Sa bawat araw na nilikha\r\nNagtatanong ba't 'di makita\r\nAng magpupuno ng ligaya\r\nKapiling kapag nag-iisa\r\nSa tuwing lungkot ay magbabanta\r\n'Di akalain na ako'y mahalin\r\n'Di napansin ng ako'y iyong sagipin\r\nNg pag-ibig mong tunay\r\nNawalay ang lumbay\r\nNgayong kapiling ka sa buhay\r\nSa'yo lamang panatag ang loob\r\nSa'yo lamang umibig ng lubusan\r\nPanalangin, ito'y panghabang-buhay\r\nPagkat sa piling mo\r\nRamdam ng puso ko\r\nSa'yo lamang ang buhay ko'y buo\r\n'Di akalain na ako'y mahalin\r\n'Di napansin ng ako'y iyong sagipin\r\nNg pag-ibig mong tunay\r\nNawalay ang lumbay\r\nNgayong kapiling ka sa buhay\r\nSa'yo lamang panatag ang loob\r\nSa'yo lamang umibig ng lubusan\r\nPanalangin, ito'y panghabang-buhay\r\nPagkat sa piling mo\r\nRamdam ng puso ko\r\nSa'yo lamang ang buhay ko'y buo\r\n'Di ko hinanap\r\nDumating ang siyang pangarap\r\n'Wag ng mawalay pa\r\nTadhanang kay ganda\r\nSa'yo lamang panatag ang loob\r\nSa'yo lamang umibig ng lubusan\r\nPanalangin, ito'y panghabang-buhay\r\nPagkat sa piling mo\r\nRamdam ng puso ko\r\nSa'yo lamang ang buhay ko'y buo\r\nPagkat sa piling mo\r\nRamdam ng puso ko\r\nSa'yo lamang ang buhay ko'y buo",
  "source": "Musixmatch"
}