{
  "track_id": "6cGHNpASOBe7imL6ZbKtOc",
  "artist": "Reynier Perez",
  "title": "Enamorate Bailando",
  "lyrics": "Enamorate bailando\r\nEnamorate conmigo\r\nYo se que estando abrazados\r\nVamos a sentir lo mismo\r\nQue la música nos lleve\r\nDonde nos lleve\n\nPor q lo que está marcado\n\nNadie puede evitarlo\n\nEnamorate bailando conmigo\n\nAsí así... Así así... Pegadito\n\nEnamorate bailando\n\nNo lo pienses no lo pienses\n\nDeja que los cuerpos hablen\n\nQue bailando ellos se entienden\n\nQue la música nos lleve\n\nDonde nos lleve\n\nPor que lo que está marcado\n\nNadie puede evitarlo\n\nEnamorate bailando conmigo\n\nAsí. Así. Así. Así... Pegadito\n\nLa pista esta lista y yo con la vista\n\nTe invito a que bailes\n\nNos llama el sonido\n\nLa musica nos mantiene\n\nA su son bailando Unidos\n\nTu cuerpo sigue llevando\n\nEl ritmo de mis latidos\n\nLo que es obvio no se explica\n\nY se ven Pegaditos\n\nQue.nos dejen el rincón\n\nPa bailarlo solitos",
  "source": "Lyrics OVH"
}