{
  "track_id": "7hzNrW4jgbgFOYBX4PXKqr",
  "artist": "Baka Not Nice",
  "title": "Gimme That Work",
  "lyrics": "Got that tip from [?] and you got them pies\r\nAll my niggas Gucci, so they down to ride\r\nLeft my mask at home, we don't do disguise\r\nGot a four fif' on my side in case they wanna try\r\nPull up, skrt (woah)\r\nGrippin' the stick when I turn (yeah)\n\nSmokin', I'm calmin' my nerves\n\nKickin' the door and I'm goin' in first\n\nFamily see me, they goin' berserk\n\nLike give me the bag and nobody get hurt\n\n\n\nGimme that work, hey (woo)\n\nGi-gi-gimme that work\n\nGimme that work, nuh\n\n'Bout to gimme that work, hey (woo)\n\nGi-gi-gimme that work, nuh\n\n'Bout to gimme that work, hey\n\nGimme that work\n\n\n\nTrust now, you know I'm up now\n\nShe see me with a bag, she wanna fuck now\n\nThey see me with a Aud', they wanna know how\n\nRollin' off a addy, I can't slow down (uh, uh, uh, woo)\n\n\n\nI robbed your bitch for the night, I might just give her the pipe\n\nI might just—\n\nI might just dip in it twice, I might just speak of a spice (yeah, yeah)\n\nShe did it back to the kitchen, whippin' and cheffin' that white (whip it, whip)\n\nTold her to pass me the scale, answer the phone\n\n\n\nAnd gimme that work, hey (woo)\n\nGi-gi-gimme that work\n\nGimme that work, nuh\n\n'Bout to gimme that work, hey (woo)\n\nGi-gi-gimme that work, nuh\n\n'Bout to gimme that work, hey\n\n\n\nGimme that work, hey (woo, woo)\n\nGi-gi-gimme that work\n\nGimme that work, nuh\n\n'Bout to gimme that work, hey (woo)\n\nGi-gi-gimme that work, nuh\n\nFuck with my money, somebody get murked\n\nGimme that work\n\n\n\nSaid, said, hey\n\nYeah\n\nYeah, yeah, hey\n\nSaid, said, hey\n\nHey\n\n\n\nGimme that work, hey (woo)\n\nGi-gi-gimme that work\n\nGimme that work, nuh\n\n'Bout to gimme that work, hey (woo)\n\nGi-gi-gimme that work, nuh\n\n'Bout to gimme that work, hey\n\n\n\nGimme that work, hey\n\nGimme that work\n\nGimme that work, nuh\n\n'Bout to gimme that work, hey\n\nGi-gi-gimme that work, nuh\n\n'Bout to gimme that work\n\nGimme that work\n\n\n\nTrust now, you know I'm up now\n\nShe see me with a bag, she wanna fuck now\n\nThey see me with a Aud', they wanna know how\n\nRollin' off a addy, I can't slow down\n\n\n\nI'm 'bout the fuckin' bags, my nigga\n\nThe two bits that made it true, my nigga\n\nNow I'm flyin' private jets with the crew, my nigga\n\nWhere the fuck where you when the judge gave me 13 years, 9 months?\n\nWhere the fuck were you?\n\nWhen my pops was in the court room in shock\n\nWhere were you when I was down below?\n\nYo, I got convicted of somethin' I ain't even fuckin' do, my nigga\n\nFuck, man\n\nWe don't do the long talkin', ayy?\n\nWe just get straight to the barkin'\n\nIt's a OVO ting",
  "source": "Lyrics OVH"
}