{
  "track_id": "380v3gb384xxUt8A3C8aqt",
  "artist": "Nina Nesbitt",
  "title": "Love Letter",
  "lyrics": "We started good, crossed our hearts, they made a promise\r\nMisunderstood, 'cause all my friends say you're dishonest\r\nYou had me questionin' what I was worth\r\nThey know and I know, now\r\nSay what you want but I know that it's on me\n\nWords that you use to anyone, anybody\n\nLie, so tonight keep it done with your sorries\n\nGet out my face, it's safe to say\n\n\n\nWhen I was your girlfriend, you said it'd be different\n\nYou wanted other girls and you want a commitment\n\nBut you couldn't get it to-to-together\n\nI'm sitting here with this love, love, love letter\n\nOh, I was your girlfriend\n\nI thought you were different\n\nI tried to make it work, gave a million chances\n\nBut I know I can do, do, do better\n\nI'm sitting here with this love, love, love letter\n\n\n\nYou'd sit at home, too keen on that marijuana\n\nPick up your clothes like you forgot I'm not your mother\n\nYeah, you were getting way too comfortable\n\nYeah, you know and I know, now\n\n\n\nSay what you want but I know that it's on me\n\nWords that you use to anyone, anybody\n\nLie, so tonight keep it done with your sorries\n\nGet out my face, it's safe to say\n\n\n\nWhen I was your girlfriend, you said it'd be different\n\nYou wanted other girls and you want a commitment\n\nBut you couldn't get it to-to-together\n\nI'm sitting here with this love, love, love letter\n\nOh, I was your girlfriend\n\nI thought you were different\n\nI tried to make it work, gave a million chances\n\nBut I know I can do, do, do better\n\nI'm sitting here with this love, love, love letter\n\n\n\nOh-oh-oh, oh-oh-oh-oh\n\nOh-oh-oh, oh-oh-oh-oh\n\nOh-oh-oh, oh-oh-oh-oh\n\nI'm sitting here with this love-love-love letter\n\nOh-oh-oh, oh-oh-oh-oh\n\n\n\nAt the time you get it I'll be out on the road\n\n'Cause I packed up all my things, put your name on the note\n\nYeah, you thought you were clever but you didn't know\n\nThat my heart left you 'bout two months ago\n\nAt the time you get it I'll be out on the road\n\n'Cause I packed up all my things, put your name on the note\n\nYeah, you thought you were clever but you didn't know\n\nThat my heart left you 'bout two months ago\n\n\n\nWhen I was your girlfriend, you said it'd be different\n\nYou wanted other girls and you want a commitment\n\nBut you couldn't get it to-to-together\n\nI'm sitting here with this love, love, love letter\n\nOh, I was your girlfriend\n\nI thought you were different\n\nI tried to make it work, gave a million chances\n\nBut I know I can do, do, do better\n\nI'm sitting here with this love, love, love letter\n\n\n\nAt the time you get it I'll be out on the road\n\n'Cause I packed up all my things, put your name on the note\n\nYeah, you thought you were clever but you didn't know\n\nI'm sitting here with this love, love, love letter",
  "source": "Lyrics OVH"
}