{
  "track_id": "0IQJvfyAOwKrcDxZgyLTny",
  "artist": "Carin Leon",
  "title": "Me La Avente",
  "lyrics": "Perdón\r\nSi destrocé tu frío y frágil corazón\r\nYo sabía que en lo profundo había amor\r\nPero ya es tarde, ya la puerta se cerró\r\nQue fui muy cruel\r\nTal vez, es cierto pero, ¿qué diablos le puedo hacer?\n\nNo se va acabar el mundo, sabes bien\n\nPero volver, eso ya no se va a poder\n\nSi me la aventé, fue por tu culpa\n\nPorque sé que un amor a huevo no resulta\n\nY porque, según tú, de todo yo tenía la culpa\n\nY mirando pa' bajo, nomás te pedía disculpas\n\nSi me la aventé, fue por venganza\n\nPa' ver si con un golpe, la mula se amansa\n\nYa no me importa si me dicen \"me voy de esta casa\"\n\nHaz lo que quieras y si muy maciza\n\nTe suplico que cumplas tus amenazas\n\nPa' que sepa cómo ruge el león\n\nSu compa Carin Leon, fierro\n\nSi me la aventé, fue por tu culpa\n\nPorque sé que un amor a huevo no resulta\n\nY porque según tú, de todo yo tenía la culpa\n\nY mirando pa' bajo, nomás te pedía disculpas\n\nSi me la aventé fue por venganza\n\nPa' ver si con un golpe, la mula se amansa\n\nYa no me importa si me dicen \"me voy de esta casa\"\n\nHaz lo que quieras y si muy maciza\n\nTe suplico que cumplas tus amenazas",
  "source": "Lyrics OVH"
}