{
  "track_id": "1ufQ1P133UDlCdxsYSio0a",
  "artist": "YUNGBLUD",
  "title": "King Charles",
  "lyrics": "Stop being a twatty, brap\r\nHappy, be fucking happy\r\nI admit I've never been broke but I have been broken\r\nShout inside, she'll switch you for a token of kindness\r\nThis one's for you King Charles, you mess with the people\n\nTook the taxes to fund the evil, sound familiar?\n\nDon't mind us, divide us, but when we need guidance, you give us the silence\n\nIt's spineless and blindless, we will buy back, not sit here smiling\n\nWhile they used to attack the student loans and the first time homes, it's time to know\n\nThey act the moment, they neglecting the young, it's really scary being under 21\n\n\n\nHoney, we want your money\n\nGet out your wallet and give us your\n\nMoney and you may as well\n\nThrow in your soul\n\n\n\nSorry, mate\n\nEh, we're taking your car, brap\n\n\n\nI see you just royal pretending, too sober to spend us\n\nYou talk about lease but then no one surrenders\n\nFrom a cynical man, we don't fucking plan\n\nWhen it all goes wrong, there'll no confession\n\nOnly a digression, a concession, a society's aggression\n\nWe're create a phenomenal compression, the heads of the youth, what do we do?\n\nWhat do we do, man, what do we do?\n\nWhat do we do, man, what do we do?\n\n\n\nHoney, we want your money\n\nGet out your wallet and give us your\n\nMoney and you may as well\n\nGive us your soul\n\n\n\nWe're taking your car now, sir\n\nWe're taking your car now, sir\n\nWe're just taking your car now, sir\n\nWe're just taking your car now, sir\n\n\n\nHoney, we want your money\n\nGet out your wallet and give us your\n\nMoney and you may as well\n\nGive us your soul, brap\n\nHoney, we want your money\n\nGet out your wallet and give us your\n\nMoney and you may as well\n\nThrow in your soul",
  "source": "Lyrics OVH"
}