{
  "track_id": "16XIuS1nOBKjGsSYzN0nD3",
  "artist": "Wiz Khalifa",
  "title": "Find A Way",
  "lyrics": "Uh, long days, gotta recharge to run the play\r\nPaper straight, come up with bars to get us paid\r\nMajor weight make it hard for them to imitate\r\nRolex tell the daytime and the date\r\nIf I eat, all my niggas gon' get a plate\r\nIf you hate, guaranteed, you ain't in the way\n\nClown shit, we don't entertain\n\nAlways been a young nigga with the vision and I'm still the same\n\nTurned an idea into a strain\n\nDo it once, I fuck with you, I respect you, you do it again\n\nNothin' but the best for the fam\n\nI don't gotta flex for the 'Gram\n\nToo many rings for my hands, so we stack 'em and stash 'em\n\nWe them fuckin' champs\n\n\n\nAyy, ayy, ayy, ayy\n\nAh-ah, uh\n\nYou ain't gotta lie to kick it\n\nYou ain't close to rich enough to be in here\n\nPapered up and stoned at every appearance\n\nMartha's Vineyard, baby left her diamond necklace behind\n\nAt the bed and breakfast, it's fine\n\nShe got that on a high, she'll steal a better one on the next one\n\nI only fuck with professionals\n\nSniper scopes and silencers stuck inside of leather sectionals\n\nWatch where you sit at, might hear that click-clack\n\nI copped the BMW six pack, M package\n\nHighway action, state mansion\n\nThat's what G's do, you smell that fire in the breeze, fool\n\nDon't you dare call this shit a part two\n\nThis a whole 'nother animal, this that mankind mandible\n\nChanel drip on your television channel\n\nCar location lit as a birthday candle\n\n\n\nPay me just like a fan do\n\nReal one so they don't know how much my shit they can handle\n\nChicks love social media, so I watch out for them scandals\n\nDon't measure that kush, give you a handful\n\nGotta grind 'cause my son hungry and the rent due\n\n\n\nWe changed how you smoke, changed how you dress\n\nYour whole life was blessed by the presence of the stoned legends\n\nHo, retrace our steps and see what you get\n\nIf you never let suckers talk you out shootin' your shot\n\nHustle with every breath, huh?\n\n\n\nA queen\n\nOunces of weed\n\nGot your own\n\nIf you at my table\n\nA queen\n\nOunces of weed\n\nGot your own\n\nIf you at my table\n\nYeah, ooh\n\nOoh, ooh-ooh-ooh\n\nOoh, ooh-ooh\n\nOoh, ooh-ooh-ooh",
  "source": "Lyrics OVH"
}